{"v":"4.6.9","fr":25,"ip":0,"op":75,"w":750,"h":560,"nm":"合成 1","ddd":0,"assets":[{"id":"image_0","w":750,"h":560,"u":"images/","p":"middle_gift_chashuibiao_img_0.png"},{"id":"image_1","w":750,"h":560,"u":"images/","p":"middle_gift_chashuibiao_img_1.png"},{"id":"image_2","w":750,"h":560,"u":"images/","p":"middle_gift_chashuibiao_img_2.png"},{"id":"image_3","w":750,"h":560,"u":"images/","p":"middle_gift_chashuibiao_img_3.png"},{"id":"image_4","w":750,"h":560,"u":"images/","p":"middle_gift_chashuibiao_img_4.png"}],"layers":[{"ddd":0,"ind":1,"ty":2,"nm":"礼物合集.png","cl":"png","refId":"image_0","ks":{"o":{"a":0,"k":100},"r":{"a":1,"k":[{"i":{"x":[0.833],"y":[0.833]},"o":{"x":[0.167],"y":[0.167]},"n":["0p833_0p833_0p167_0p167"],"t":40,"s":[0],"e":[15]},{"i":{"x":[0.833],"y":[0.833]},"o":{"x":[0.167],"y":[0.167]},"n":["0p833_0p833_0p167_0p167"],"t":46,"s":[15],"e":[0]},{"i":{"x":[0.833],"y":[0.833]},"o":{"x":[0.167],"y":[0.167]},"n":["0p833_0p833_0p167_0p167"],"t":52,"s":[0],"e":[15]},{"i":{"x":[0.833],"y":[0.833]},"o":{"x":[0.167],"y":[0.167]},"n":["0p833_0p833_0p167_0p167"],"t":58,"s":[15],"e":[0]},{"i":{"x":[0.833],"y":[0.833]},"o":{"x":[0.167],"y":[0.167]},"n":["0p833_0p833_0p167_0p167"],"t":64,"s":[0],"e":[15]},{"t":70}]},"p":{"a":0,"k":[227,329,0]},"a":{"a":0,"k":[227,329,0]},"s":{"a":1,"k":[{"i":{"x":[0.833,0.833,0.833],"y":[0.833,0.833,0.833]},"o":{"x":[0.167,0.167,0.167],"y":[0.167,0.167,0.167]},"n":["0p833_0p833_0p167_0p167","0p833_0p833_0p167_0p167","0p833_0p833_0p167_0p167"],"t":1,"s":[20,20,100],"e":[105,105,100]},{"i":{"x":[0.833,0.833,0.833],"y":[0.833,0.833,0.833]},"o":{"x":[0.167,0.167,0.167],"y":[0.167,0.167,0.167]},"n":["0p833_0p833_0p167_0p167","0p833_0p833_0p167_0p167","0p833_0p833_0p167_0p167"],"t":7,"s":[105,105,100],"e":[97,97,100]},{"i":{"x":[0.833,0.833,0.833],"y":[0.833,0.833,0.833]},"o":{"x":[0.167,0.167,0.167],"y":[0.167,0.167,0.167]},"n":["0p833_0p833_0p167_0p167","0p833_0p833_0p167_0p167","0p833_0p833_0p167_0p167"],"t":11,"s":[97,97,100],"e":[100,100,100]},{"t":13}]}},"ao":0,"ip":1,"op":75,"st":0,"bm":0,"sr":1},{"ddd":0,"ind":2,"ty":2,"nm":"shui.png","cl":"png","refId":"image_1","ks":{"o":{"a":0,"k":100},"r":{"a":1,"k":[{"i":{"x":[0.833],"y":[0.833]},"o":{"x":[0.167],"y":[0.167]},"n":["0p833_0p833_0p167_0p167"],"t":16,"s":[360],"e":[0]},{"t":23}]},"p":{"a":0,"k":[387,305,0]},"a":{"a":0,"k":[387,305,0]},"s":{"a":1,"k":[{"i":{"x":[0.833,0.833,0.833],"y":[0.833,0.833,0.833]},"o":{"x":[0.167,0.167,0.167],"y":[0.167,0.167,0.167]},"n":["0p833_0p833_0p167_0p167","0p833_0p833_0p167_0p167","0p833_0p833_0p167_0p167"],"t":16,"s":[20,20,100],"e":[100,100,100]},{"t":23}]}},"ao":0,"ip":16,"op":75,"st":0,"bm":0,"sr":1},{"ddd":0,"ind":3,"ty":2,"nm":"biao1.png","cl":"png","refId":"image_2","ks":{"o":{"a":1,"k":[{"i":{"x":[0.833],"y":[0.833]},"o":{"x":[0.167],"y":[0.167]},"n":["0p833_0p833_0p167_0p167"],"t":26,"s":[0],"e":[100]},{"t":30}]},"r":{"a":1,"k":[{"i":{"x":[0.833],"y":[0.833]},"o":{"x":[0.167],"y":[0.167]},"n":["0p833_0p833_0p167_0p167"],"t":40,"s":[0],"e":[360]},{"t":70}]},"p":{"a":1,"k":[{"i":{"x":0.833,"y":0.833},"o":{"x":0.167,"y":0.167},"n":"0p833_0p833_0p167_0p167","t":26,"s":[597,186,0],"e":[597,316,0],"to":[0,21.6666660308838,0],"ti":[0,-20,0]},{"i":{"x":0.833,"y":0.833},"o":{"x":0.167,"y":0.167},"n":"0p833_0p833_0p167_0p167","t":32,"s":[597,316,0],"e":[597,306,0],"to":[0,20,0],"ti":[0,1.66666662693024,0]},{"t":35}]},"a":{"a":0,"k":[597,306,0]},"s":{"a":0,"k":[100,100,100]}},"ao":0,"ip":26,"op":75,"st":0,"bm":0,"sr":1},{"ddd":0,"ind":4,"ty":2,"nm":"biao.png","cl":"png","refId":"image_3","ks":{"o":{"a":1,"k":[{"i":{"x":[0.833],"y":[0.833]},"o":{"x":[0.167],"y":[0.167]},"n":["0p833_0p833_0p167_0p167"],"t":26,"s":[0],"e":[100]},{"t":30}]},"r":{"a":0,"k":0},"p":{"a":1,"k":[{"i":{"x":0.833,"y":0.833},"o":{"x":0.167,"y":0.167},"n":"0p833_0p833_0p167_0p167","t":26,"s":[533,168,0],"e":[533,298,0],"to":[0,21.6666660308838,0],"ti":[0,-20,0]},{"i":{"x":0.833,"y":0.833},"o":{"x":0.167,"y":0.167},"n":"0p833_0p833_0p167_0p167","t":32,"s":[533,298,0],"e":[533,288,0],"to":[0,20,0],"ti":[0,1.66666662693024,0]},{"t":35}]},"a":{"a":0,"k":[533,288,0]},"s":{"a":0,"k":[100,100,100]}},"ao":0,"ip":26,"op":75,"st":0,"bm":0,"sr":1},{"ddd":0,"ind":5,"ty":2,"nm":"cha.png","cl":"png","refId":"image_4","ks":{"o":{"a":0,"k":100},"r":{"a":0,"k":0},"p":{"a":0,"k":[227,327,0]},"a":{"a":0,"k":[227,327,0]},"s":{"a":1,"k":[{"i":{"x":[0.833,0.833,0.833],"y":[0.833,0.833,0.833]},"o":{"x":[0.167,0.167,0.167],"y":[0.167,0.167,0.167]},"n":["0p833_0p833_0p167_0p167","0p833_0p833_0p167_0p167","0p833_0p833_0p167_0p167"],"t":1,"s":[20,20,100],"e":[105,105,100]},{"i":{"x":[0.833,0.833,0.833],"y":[0.833,0.833,0.833]},"o":{"x":[0.167,0.167,0.167],"y":[0.167,0.167,0.167]},"n":["0p833_0p833_0p167_0p167","0p833_0p833_0p167_0p167","0p833_0p833_0p167_0p167"],"t":7,"s":[105,105,100],"e":[97,97,100]},{"i":{"x":[0.833,0.833,0.833],"y":[0.833,0.833,0.833]},"o":{"x":[0.167,0.167,0.167],"y":[0.167,0.167,0.167]},"n":["0p833_0p833_0p167_0p167","0p833_0p833_0p167_0p167","0p833_0p833_0p167_0p167"],"t":11,"s":[97,97,100],"e":[100,100,100]},{"t":13}]}},"ao":0,"ip":1,"op":75,"st":0,"bm":0,"sr":1}]}
