{"assets":[{"id":"image_0","w":125,"h":102,"u":"images/","p":"dlw_tb_yjh_img_0.png"},{"id":"image_1","w":125,"h":102,"u":"images/","p":"dlw_tb_yjh_img_1.png"},{"id":"image_2","w":125,"h":102,"u":"images/","p":"dlw_tb_yjh_img_2.png"},{"id":"image_3","w":125,"h":102,"u":"images/","p":"dlw_tb_yjh_img_3.png"},{"id":"image_4","w":125,"h":102,"u":"images/","p":"dlw_tb_yjh_img_4.png"},{"id":"image_5","w":125,"h":102,"u":"images/","p":"dlw_tb_yjh_img_5.png"},{"id":"image_6","w":125,"h":102,"u":"images/","p":"dlw_tb_yjh_img_6.png"},{"id":"image_7","w":125,"h":102,"u":"images/","p":"dlw_tb_yjh_img_7.png"},{"id":"image_8","w":125,"h":102,"u":"images/","p":"dlw_tb_yjh_img_8.png"},{"id":"image_9","w":125,"h":102,"u":"images/","p":"dlw_tb_yjh_img_9.png"}],"layers":[{"ddd":0,"ind":0,"ty":2,"nm":"dlw_tb_yj01_0001.png","cl":"png","refId":"image_0","ks":{"o":{"k":100},"r":{"k":0},"p":{"k":[54,46,0]},"a":{"k":[62.5,51,0]},"s":{"k":[82,82,100]}},"ao":0,"ip":0,"op":1,"st":0,"bm":0,"sr":1},{"ddd":0,"ind":1,"ty":2,"nm":"dlw_tb_yj01_0002.png","cl":"png","refId":"image_1","ks":{"o":{"k":100},"r":{"k":0},"p":{"k":[54,46,0]},"a":{"k":[62.5,51,0]},"s":{"k":[82,82,100]}},"ao":0,"ip":1,"op":2,"st":1,"bm":0,"sr":1},{"ddd":0,"ind":2,"ty":2,"nm":"dlw_tb_yj01_0003.png","cl":"png","refId":"image_2","ks":{"o":{"k":100},"r":{"k":0},"p":{"k":[54,46,0]},"a":{"k":[62.5,51,0]},"s":{"k":[82,82,100]}},"ao":0,"ip":2,"op":3,"st":2,"bm":0,"sr":1},{"ddd":0,"ind":3,"ty":2,"nm":"dlw_tb_yj01_0004.png","cl":"png","refId":"image_3","ks":{"o":{"k":100},"r":{"k":0},"p":{"k":[54,46,0]},"a":{"k":[62.5,51,0]},"s":{"k":[82,82,100]}},"ao":0,"ip":3,"op":4,"st":3,"bm":0,"sr":1},{"ddd":0,"ind":4,"ty":2,"nm":"dlw_tb_yj01_0005.png","cl":"png","refId":"image_4","ks":{"o":{"k":100},"r":{"k":0},"p":{"k":[54,46,0]},"a":{"k":[62.5,51,0]},"s":{"k":[82,82,100]}},"ao":0,"ip":4,"op":5,"st":4,"bm":0,"sr":1},{"ddd":0,"ind":5,"ty":2,"nm":"dlw_tb_yj01_0006.png","cl":"png","refId":"image_5","ks":{"o":{"k":100},"r":{"k":0},"p":{"k":[54,46,0]},"a":{"k":[62.5,51,0]},"s":{"k":[82,82,100]}},"ao":0,"ip":5,"op":6,"st":5,"bm":0,"sr":1},{"ddd":0,"ind":6,"ty":2,"nm":"dlw_tb_yj01_0007.png","cl":"png","refId":"image_6","ks":{"o":{"k":100},"r":{"k":0},"p":{"k":[54,46,0]},"a":{"k":[62.5,51,0]},"s":{"k":[82,82,100]}},"ao":0,"ip":6,"op":7,"st":6,"bm":0,"sr":1},{"ddd":0,"ind":7,"ty":2,"nm":"dlw_tb_yj01_0008.png","cl":"png","refId":"image_7","ks":{"o":{"k":100},"r":{"k":0},"p":{"k":[54,46,0]},"a":{"k":[62.5,51,0]},"s":{"k":[82,82,100]}},"ao":0,"ip":7,"op":8,"st":7,"bm":0,"sr":1},{"ddd":0,"ind":8,"ty":2,"nm":"dlw_tb_yj01_0009.png","cl":"png","refId":"image_8","ks":{"o":{"k":100},"r":{"k":0},"p":{"k":[54,46,0]},"a":{"k":[62.5,51,0]},"s":{"k":[82,82,100]}},"ao":0,"ip":8,"op":9,"st":8,"bm":0,"sr":1},{"ddd":0,"ind":9,"ty":2,"nm":"dlw_tb_yj01_0010.png","cl":"png","refId":"image_9","ks":{"o":{"k":100},"r":{"k":0},"p":{"k":[54,46,0]},"a":{"k":[62.5,51,0]},"s":{"k":[82,82,100]}},"ao":0,"ip":9,"op":10,"st":9,"bm":0,"sr":1}],"v":"4.5.3","ddd":0,"ip":0,"op":10,"fr":8,"w":108,"h":92}
